{"v":"5.7.11","fr":30,"ip":0,"op":120,"w":172,"h":172,"nm":"onb_icon_01_clip","ddd":0,"assets":[],"layers":[{"ddd":0,"ind":1,"ty":4,"nm":"hand contornos","sr":1,"ks":{"o":{"a":1,"k":[{"i":{"x":[0.833],"y":[0.833]},"o":{"x":[0.167],"y":[0.167]},"t":0,"s":[0]},{"t":10,"s":[100]}],"ix":11},"r":{"a":0,"k":0,"ix":10},"p":{"a":1,"k":[{"i":{"x":0.833,"y":0.833},"o":{"x":0.167,"y":0.167},"t":0,"s":[86,162.592,0],"to":[0,0,0],"ti":[0,0,0]},{"i":{"x":0.833,"y":0.833},"o":{"x":0.167,"y":0.167},"t":10,"s":[86,162.592,0],"to":[0,-10.833,0],"ti":[0,10.833,0]},{"i":{"x":0.833,"y":0.833},"o":{"x":0.167,"y":0.167},"t":20,"s":[86,97.592,0],"to":[0,0,0],"ti":[0,0,0]},{"i":{"x":0.833,"y":0.833},"o":{"x":0.167,"y":0.167},"t":30,"s":[86,97.592,0],"to":[5,-1.667,0],"ti":[-5,1.667,0]},{"t":50,"s":[116,87.592,0]}],"ix":2,"l":2},"a":{"a":0,"k":[86,97.592,0],"ix":1,"l":2},"s":{"a":0,"k":[100,100,100],"ix":6,"l":2}},"ao":0,"hasMask":true,"masksProperties":[{"inv":false,"mode":"a","pt":{"a":1,"k":[{"i":{"x":0.833,"y":0.833},"o":{"x":0.167,"y":0.167},"t":-2,"s":[{"i":[[47.358,0],[0,-47.358],[-47.358,0],[0,47.358]],"o":[[-47.358,0],[0,47.358],[47.358,0],[0,-47.358]],"v":[[86.75,0.5],[1,86.25],[86.75,172],[172.5,86.25]],"c":true}]},{"i":{"x":0.833,"y":0.833},"o":{"x":0.167,"y":0.167},"t":-1,"s":[{"i":[[47.358,0],[0,-47.358],[-47.358,0],[0,47.358]],"o":[[-47.358,0],[0,47.358],[47.358,0],[0,-47.358]],"v":[[86.75,2.083],[1,87.833],[86.75,173.583],[172.5,87.833]],"c":true}]},{"i":{"x":0.833,"y":0.833},"o":{"x":0.167,"y":0.167},"t":0,"s":[{"i":[[47.358,0],[0,-47.358],[-47.358,0],[0,47.358]],"o":[[-47.358,0],[0,47.358],[47.358,0],[0,-47.358]],"v":[[86.75,-64.5],[1,21.25],[86.75,107],[172.5,21.25]],"c":true}]},{"i":{"x":0.833,"y":0.833},"o":{"x":0.167,"y":0.167},"t":10,"s":[{"i":[[47.358,0],[0,-47.358],[-47.358,0],[0,47.358]],"o":[[-47.358,0],[0,47.358],[47.358,0],[0,-47.358]],"v":[[86.75,-64.5],[1,21.25],[86.75,107],[172.5,21.25]],"c":true}]},{"i":{"x":0.833,"y":0.833},"o":{"x":0.167,"y":0.167},"t":20,"s":[{"i":[[47.358,0],[0,-47.358],[-47.358,0],[0,47.358]],"o":[[-47.358,0],[0,47.358],[47.358,0],[0,-47.358]],"v":[[86.75,0.5],[1,86.25],[86.75,172],[172.5,86.25]],"c":true}]},{"i":{"x":0.833,"y":0.833},"o":{"x":0.167,"y":0.167},"t":30,"s":[{"i":[[47.358,0],[0,-47.358],[-47.358,0],[0,47.358]],"o":[[-47.358,0],[0,47.358],[47.358,0],[0,-47.358]],"v":[[86.75,0.5],[1,86.25],[86.75,172],[172.5,86.25]],"c":true}]},{"t":50,"s":[{"i":[[47.358,0],[0,-47.358],[-47.358,0],[0,47.358]],"o":[[-47.358,0],[0,47.358],[47.358,0],[0,-47.358]],"v":[[56.75,10.5],[-29,96.25],[56.75,182],[142.5,96.25]],"c":true}]}],"ix":1},"o":{"a":0,"k":100,"ix":3},"x":{"a":0,"k":0,"ix":4},"nm":"Máscara 1"}],"shapes":[{"ty":"gr","it":[{"ind":0,"ty":"sh","ix":1,"ks":{"a":0,"k":{"i":[[0,0],[0,0],[1.621,4.875],[1.856,4.506],[0,0],[0.395,0.775],[0,0],[0,0],[0,0],[0,0],[3.242,-1.634],[0.257,-2.082],[2.298,-1.157],[-0.308,-2.578],[3.056,-1.54],[-0.592,-2.737],[0,0],[3.535,-1.78],[-1.78,-3.535],[0,0],[4.83,1.19],[1.005,-4.083],[-4.084,-1.006],[-6.914,-5.368],[-1.632,0],[-0.911,0.368],[-4.148,-0.303]],"o":[[0,0],[-1.324,-4.062],[2.168,-4.124],[0,0],[-0.035,-0.824],[0,0],[0,0],[0,0],[0,0],[-1.55,-3.036],[-2.104,1.059],[-1.88,-1.315],[-2.59,1.305],[-1.703,-2.654],[-2.774,1.397],[0,0],[-1.779,-3.536],[-3.535,1.779],[0,0],[-5.621,-3.613],[-4.081,-1.004],[-1.006,4.083],[5.086,1.252],[1.389,1.079],[0.978,0],[3.655,1.967],[0,0]],"v":[[8.885,43.655],[42.938,34.606],[38.248,20.413],[39.482,6.909],[34.364,-5.361],[33.729,-7.782],[31.679,-11.798],[30.965,-13.509],[30.84,-13.442],[26.041,-22.843],[17.376,-25.381],[13.697,-20.274],[6.907,-20.671],[3.223,-14.113],[-5.15,-16.149],[-8.742,-9.047],[-23.466,-38.288],[-33.088,-41.466],[-36.265,-31.844],[-15.942,8.52],[-32.718,0.192],[-41.932,5.765],[-36.359,14.98],[-12.335,29.724],[-7.67,31.326],[-4.811,30.759],[7.03,34.207]],"c":true},"ix":2},"nm":"Trazado 1","mn":"ADBE Vector Shape - Group","hd":false},{"ty":"fl","c":{"a":0,"k":[0.980000035903,0.745000023935,0.39199999641,1],"ix":4},"o":{"a":0,"k":100,"ix":5},"r":1,"bm":0,"nm":"Relleno 1","mn":"ADBE Vector Graphic - Fill","hd":false},{"ty":"tr","p":{"a":0,"k":[111.549,151.938],"ix":2},"a":{"a":0,"k":[0,0],"ix":1},"s":{"a":0,"k":[100,100],"ix":3},"r":{"a":0,"k":0,"ix":6},"o":{"a":0,"k":100,"ix":7},"sk":{"a":0,"k":0,"ix":4},"sa":{"a":0,"k":0,"ix":5},"nm":"Transformar"}],"nm":"Grupo 1","np":4,"cix":2,"bm":0,"ix":1,"mn":"ADBE Vector Group","hd":false}],"ip":0,"op":120,"st":0,"bm":0},{"ddd":0,"ind":2,"ty":4,"nm":"arrow contornos","sr":1,"ks":{"o":{"a":1,"k":[{"i":{"x":[0.833],"y":[0.833]},"o":{"x":[0.167],"y":[0.167]},"t":40,"s":[0]},{"i":{"x":[0.833],"y":[0.833]},"o":{"x":[0.167],"y":[0.167]},"t":50,"s":[100]},{"i":{"x":[0.833],"y":[0.833]},"o":{"x":[0.167],"y":[0.167]},"t":60,"s":[0]},{"i":{"x":[0.833],"y":[0.833]},"o":{"x":[0.167],"y":[0.167]},"t":70,"s":[0]},{"i":{"x":[0.833],"y":[0.833]},"o":{"x":[0.167],"y":[0.167]},"t":80,"s":[100]},{"t":90,"s":[0]}],"ix":11},"r":{"a":0,"k":0,"ix":10},"p":{"a":1,"k":[{"i":{"x":0.833,"y":0.833},"o":{"x":0.167,"y":0.167},"t":40,"s":[76,102.592,0],"to":[3.333,-1.333,0],"ti":[0,0,0]},{"i":{"x":0.833,"y":0.833},"o":{"x":0.167,"y":0.167},"t":60,"s":[96,94.592,0],"to":[0,0,0],"ti":[0,0,0]},{"i":{"x":0.833,"y":0.833},"o":{"x":0.167,"y":0.167},"t":70,"s":[76,102.592,0],"to":[0,0,0],"ti":[-3.333,1.333,0]},{"t":90,"s":[96,94.592,0]}],"ix":2,"l":2},"a":{"a":0,"k":[86,97.592,0],"ix":1,"l":2},"s":{"a":0,"k":[100,100,100],"ix":6,"l":2}},"ao":0,"shapes":[{"ty":"gr","it":[{"ind":0,"ty":"sh","ix":1,"ks":{"a":0,"k":{"i":[[0,0],[0.245,-0.7],[-0.7,-0.246],[0,0],[0,0],[-0.701,-0.246],[-0.148,0],[-0.193,0.553],[0,0]],"o":[[-0.7,-0.246],[-0.246,0.7],[0,0],[0,0],[-0.246,0.7],[0.147,0.052],[0.555,0],[0,0],[0,0]],"v":[[-3.339,-6.157],[-5.051,-5.333],[-4.23,-3.62],[1.872,-1.48],[-0.266,4.614],[0.557,6.326],[1.002,6.403],[2.269,5.503],[5.298,-3.126]],"c":true},"ix":2},"nm":"Trazado 1","mn":"ADBE Vector Shape - Group","hd":false},{"ty":"fl","c":{"a":0,"k":[0.019999999626,0.745000023935,0.313999998803,1],"ix":4},"o":{"a":0,"k":100,"ix":5},"r":1,"bm":0,"nm":"Relleno 1","mn":"ADBE Vector Graphic - Fill","hd":false},{"ty":"tr","p":{"a":0,"k":[100.002,106.841],"ix":2},"a":{"a":0,"k":[0,0],"ix":1},"s":{"a":0,"k":[100,100],"ix":3},"r":{"a":0,"k":0,"ix":6},"o":{"a":0,"k":100,"ix":7},"sk":{"a":0,"k":0,"ix":4},"sa":{"a":0,"k":0,"ix":5},"nm":"Transformar"}],"nm":"Grupo 1","np":4,"cix":2,"bm":0,"ix":1,"mn":"ADBE Vector Group","hd":false},{"ty":"gr","it":[{"ind":0,"ty":"sh","ix":1,"ks":{"a":0,"k":{"i":[[0.246,-0.7],[-0.701,-0.246],[0,0],[0,0],[-0.7,-0.246],[-0.147,0],[-0.194,0.553],[0,0],[0,0]],"o":[[-0.246,0.7],[0,0],[0,0],[-0.246,0.7],[0.147,0.052],[0.555,0],[0,0],[0,0],[-0.7,-0.246]],"v":[[-5.051,-5.333],[-4.229,-3.62],[1.872,-1.479],[-0.266,4.613],[0.557,6.326],[1.001,6.402],[2.27,5.503],[5.298,-3.126],[-3.339,-6.156]],"c":true},"ix":2},"nm":"Trazado 1","mn":"ADBE Vector Shape - Group","hd":false},{"ty":"fl","c":{"a":0,"k":[0.019999999626,0.745000023935,0.313999998803,1],"ix":4},"o":{"a":0,"k":100,"ix":5},"r":1,"bm":0,"nm":"Relleno 1","mn":"ADBE Vector Graphic - Fill","hd":false},{"ty":"tr","p":{"a":0,"k":[92.233,110.574],"ix":2},"a":{"a":0,"k":[0,0],"ix":1},"s":{"a":0,"k":[100,100],"ix":3},"r":{"a":0,"k":0,"ix":6},"o":{"a":0,"k":100,"ix":7},"sk":{"a":0,"k":0,"ix":4},"sa":{"a":0,"k":0,"ix":5},"nm":"Transformar"}],"nm":"Grupo 2","np":4,"cix":2,"bm":0,"ix":2,"mn":"ADBE Vector Group","hd":false}],"ip":0,"op":120,"st":0,"bm":0},{"ddd":0,"ind":3,"ty":4,"nm":"dot contornos","sr":1,"ks":{"o":{"a":1,"k":[{"i":{"x":[0.833],"y":[0.833]},"o":{"x":[0.167],"y":[0.167]},"t":0,"s":[0]},{"t":10,"s":[100]}],"ix":11},"r":{"a":0,"k":0,"ix":10},"p":{"a":0,"k":[86,97.592,0],"ix":2,"l":2},"a":{"a":0,"k":[86,97.592,0],"ix":1,"l":2},"s":{"a":0,"k":[100,100,100],"ix":6,"l":2}},"ao":0,"shapes":[{"ty":"gr","it":[{"ind":0,"ty":"sh","ix":1,"ks":{"a":0,"k":{"i":[[-2.53,-5.267],[5.267,-2.529],[2.532,5.267],[-5.266,2.531]],"o":[[2.531,5.266],[-5.266,2.531],[-2.531,-5.267],[5.267,-2.53]],"v":[[9.535,-4.582],[4.582,9.535],[-9.536,4.583],[-4.583,-9.535]],"c":true},"ix":2},"nm":"Trazado 1","mn":"ADBE Vector Shape - Group","hd":false},{"ty":"fl","c":{"a":0,"k":[0.019999999626,0.745000023935,0.313999998803,1],"ix":4},"o":{"a":0,"k":100,"ix":5},"r":1,"bm":0,"nm":"Relleno 1","mn":"ADBE Vector Graphic - Fill","hd":false},{"ty":"tr","p":{"a":0,"k":[79.976,116.608],"ix":2},"a":{"a":0,"k":[0,0],"ix":1},"s":{"a":0,"k":[100,100],"ix":3},"r":{"a":0,"k":0,"ix":6},"o":{"a":0,"k":100,"ix":7},"sk":{"a":0,"k":0,"ix":4},"sa":{"a":0,"k":0,"ix":5},"nm":"Transformar"}],"nm":"Grupo 1","np":4,"cix":2,"bm":0,"ix":1,"mn":"ADBE Vector Group","hd":false}],"ip":0,"op":120,"st":0,"bm":0},{"ddd":0,"ind":4,"ty":4,"nm":"dot contornos","sr":1,"ks":{"o":{"a":1,"k":[{"i":{"x":[0.833],"y":[0.833]},"o":{"x":[0.167],"y":[0.167]},"t":0,"s":[0]},{"t":10,"s":[100]}],"ix":11},"r":{"a":0,"k":0,"ix":10},"p":{"a":0,"k":[86,97.592,0],"ix":2,"l":2},"a":{"a":0,"k":[86,97.592,0],"ix":1,"l":2},"s":{"a":0,"k":[100,100,100],"ix":6,"l":2}},"ao":0,"shapes":[{"ty":"gr","it":[{"ind":0,"ty":"sh","ix":1,"ks":{"a":0,"k":{"i":[[-2.53,-5.266],[5.266,-2.531],[2.531,5.267],[-5.267,2.53]],"o":[[2.53,5.266],[-5.267,2.53],[-2.532,-5.266],[5.265,-2.531]],"v":[[9.536,-4.582],[4.583,9.535],[-9.535,4.582],[-4.581,-9.535]],"c":true},"ix":2},"nm":"Trazado 1","mn":"ADBE Vector Shape - Group","hd":false},{"ty":"fl","c":{"a":0,"k":[0,0.224000010771,0.651000019148,1],"ix":4},"o":{"a":0,"k":100,"ix":5},"r":1,"bm":0,"nm":"Relleno 1","mn":"ADBE Vector Graphic - Fill","hd":false},{"ty":"tr","p":{"a":0,"k":[108.546,102.852],"ix":2},"a":{"a":0,"k":[0,0],"ix":1},"s":{"a":0,"k":[100,100],"ix":3},"r":{"a":0,"k":0,"ix":6},"o":{"a":0,"k":100,"ix":7},"sk":{"a":0,"k":0,"ix":4},"sa":{"a":0,"k":0,"ix":5},"nm":"Transformar"}],"nm":"Grupo 1","np":4,"cix":2,"bm":0,"ix":1,"mn":"ADBE Vector Group","hd":false}],"ip":0,"op":120,"st":0,"bm":0},{"ddd":0,"ind":5,"ty":4,"nm":"S/ contornos","sr":1,"ks":{"o":{"a":1,"k":[{"i":{"x":[0.833],"y":[0.833]},"o":{"x":[0.167],"y":[0.167]},"t":0,"s":[0]},{"t":10,"s":[100]}],"ix":11},"r":{"a":0,"k":0,"ix":10},"p":{"a":0,"k":[86,97.592,0],"ix":2,"l":2},"a":{"a":0,"k":[86,97.592,0],"ix":1,"l":2},"s":{"a":0,"k":[100,100,100],"ix":6,"l":2}},"ao":0,"shapes":[{"ty":"gr","it":[{"ind":0,"ty":"sh","ix":1,"ks":{"a":0,"k":{"i":[[-0.029,0.014],[-0.066,-0.138],[-0.029,-0.171],[0,0],[0,0],[0.079,-0.038],[0.099,0],[0.05,0.018],[0.063,0.135],[0.021,0.15],[0,0],[0,0]],"o":[[0.479,-0.227],[0.035,0.074],[0,0],[0,0],[-0.028,0.077],[-0.116,0.056],[-0.057,0],[-0.12,-0.043],[-0.037,-0.079],[0,0],[0,0],[0.031,-0.092]],"v":[[1.663,-3.627],[2.415,-3.414],[2.508,-3.055],[3.45,3.392],[3.43,3.453],[3.224,3.628],[2.901,3.709],[2.741,3.684],[2.465,3.417],[2.372,3.056],[1.437,-3.389],[1.458,-3.448]],"c":true},"ix":2},"nm":"Trazado 1","mn":"ADBE Vector Shape - Group","hd":false},{"ind":1,"ty":"sh","ix":2,"ks":{"a":0,"k":{"i":[[-0.524,0.248],[-0.192,-0.408],[0.093,-0.084],[0,0],[0,0],[0.466,-0.222],[-0.172,-0.362],[-0.712,0.158],[0,0],[-0.485,-1.024],[1.178,-0.558],[0.374,0],[0.13,0.274],[-0.114,0.11],[0,0],[0,0],[-0.541,0.257],[0.253,0.532],[0.735,-0.161],[0.543,1.143],[-0.206,0.432]],"o":[[1.145,-0.544],[0.148,0.31],[0,0],[0,0],[-0.418,-0.24],[-0.518,0.247],[0.179,0.377],[0,0],[0.867,-0.194],[0.452,0.95],[-0.49,0.234],[-0.574,0],[-0.129,-0.271],[0,0],[0,0],[0.492,0.285],[0.336,-0.16],[-0.194,-0.406],[-0.638,0.141],[-0.204,-0.43],[0.206,-0.431]],"v":[[-2.179,-1.855],[0.036,-1.717],[-0.13,-0.978],[-0.209,-0.907],[-0.318,-0.95],[-1.753,-0.98],[-2.323,0.022],[-1.107,0.188],[-1.003,0.165],[1.407,0.905],[0.232,3.352],[-1.078,3.678],[-2.185,3.185],[-2.032,2.472],[-1.957,2.4],[-1.838,2.432],[-0.192,2.477],[0.422,1.437],[-0.968,1.269],[-3.299,0.52],[-3.295,-0.817]],"c":true},"ix":2},"nm":"Trazado 2","mn":"ADBE Vector Shape - Group","hd":false},{"ty":"mm","mm":1,"nm":"Combinar trazados 1","mn":"ADBE Vector Filter - Merge","hd":false},{"ty":"fl","c":{"a":0,"k":[1,1,1,1],"ix":4},"o":{"a":0,"k":100,"ix":5},"r":1,"bm":0,"nm":"Relleno 1","mn":"ADBE Vector Graphic - Fill","hd":false},{"ty":"tr","p":{"a":0,"k":[92.752,74.782],"ix":2},"a":{"a":0,"k":[0,0],"ix":1},"s":{"a":0,"k":[100,100],"ix":3},"r":{"a":0,"k":0,"ix":6},"o":{"a":0,"k":100,"ix":7},"sk":{"a":0,"k":0,"ix":4},"sa":{"a":0,"k":0,"ix":5},"nm":"Transformar"}],"nm":"Grupo 1","np":6,"cix":2,"bm":0,"ix":1,"mn":"ADBE Vector Group","hd":false}],"ip":0,"op":120,"st":0,"bm":0},{"ddd":0,"ind":6,"ty":4,"nm":"dot contornos","sr":1,"ks":{"o":{"a":1,"k":[{"i":{"x":[0.833],"y":[0.833]},"o":{"x":[0.167],"y":[0.167]},"t":0,"s":[0]},{"t":10,"s":[100]}],"ix":11},"r":{"a":0,"k":0,"ix":10},"p":{"a":0,"k":[86,97.592,0],"ix":2,"l":2},"a":{"a":0,"k":[86,97.592,0],"ix":1,"l":2},"s":{"a":0,"k":[100,100,100],"ix":6,"l":2}},"ao":0,"shapes":[{"ty":"gr","it":[{"ind":0,"ty":"sh","ix":1,"ks":{"a":0,"k":{"i":[[-2.023,-4.259],[4.261,-2.023],[2.024,4.261],[-4.259,2.024]],"o":[[2.024,4.259],[-4.26,2.023],[-2.023,-4.259],[4.261,-2.023]],"v":[[7.713,-3.664],[3.663,7.713],[-7.714,3.663],[-3.665,-7.714]],"c":true},"ix":2},"nm":"Trazado 1","mn":"ADBE Vector Shape - Group","hd":false},{"ty":"fl","c":{"a":0,"k":[0,0.224000010771,0.651000019148,1],"ix":4},"o":{"a":0,"k":100,"ix":5},"r":1,"bm":0,"nm":"Relleno 1","mn":"ADBE Vector Graphic - Fill","hd":false},{"ty":"tr","p":{"a":0,"k":[93.098,74.869],"ix":2},"a":{"a":0,"k":[0,0],"ix":1},"s":{"a":0,"k":[100,100],"ix":3},"r":{"a":0,"k":0,"ix":6},"o":{"a":0,"k":100,"ix":7},"sk":{"a":0,"k":0,"ix":4},"sa":{"a":0,"k":0,"ix":5},"nm":"Transformar"}],"nm":"Grupo 1","np":4,"cix":2,"bm":0,"ix":1,"mn":"ADBE Vector Group","hd":false}],"ip":0,"op":120,"st":0,"bm":0},{"ddd":0,"ind":7,"ty":4,"nm":"pig contornos","sr":1,"ks":{"o":{"a":1,"k":[{"i":{"x":[0.833],"y":[0.833]},"o":{"x":[0.167],"y":[0.167]},"t":0,"s":[0]},{"t":10,"s":[100]}],"ix":11},"r":{"a":0,"k":0,"ix":10},"p":{"a":0,"k":[86,97.592,0],"ix":2,"l":2},"a":{"a":0,"k":[86,97.592,0],"ix":1,"l":2},"s":{"a":0,"k":[100,100,100],"ix":6,"l":2}},"ao":0,"shapes":[{"ty":"gr","it":[{"ind":0,"ty":"sh","ix":1,"ks":{"a":0,"k":{"i":[[0.3,-0.627],[0.627,0.301],[-0.302,0.628],[-0.627,-0.301]],"o":[[-0.302,0.629],[-0.628,-0.302],[0.3,-0.628],[0.629,0.303]],"v":[[-6.811,-1.882],[-8.492,-1.291],[-9.083,-2.974],[-7.403,-3.565]],"c":true},"ix":2},"nm":"Trazado 1","mn":"ADBE Vector Shape - Group","hd":false},{"ind":1,"ty":"sh","ix":2,"ks":{"a":0,"k":{"i":[[-0.008,0.001],[-0.083,-0.009],[-0.013,-0.001],[-0.072,-0.023],[-0.014,-0.005],[-0.073,-0.039],[-0.014,-0.009],[-0.066,-0.054],[0.121,-0.143],[0.524,0.434],[0.056,0.065],[0.012,0.014],[0.04,0.073],[0.006,0.011],[0.025,0.075],[0.005,0.012],[0.012,0.082],[0.001,0.006]],"o":[[0.082,-0.003],[0.013,0.001],[0.075,0.011],[0.014,0.004],[0.077,0.026],[0.016,0.009],[0.075,0.043],[0.524,0.435],[-0.118,0.144],[-0.067,-0.055],[-0.01,-0.014],[-0.051,-0.065],[-0.007,-0.01],[-0.036,-0.068],[-0.004,-0.01],[-0.024,-0.079],[-0.001,-0.007],[0.007,-0.001]],"v":[[13.851,-14.221],[14.1,-14.214],[14.139,-14.208],[14.361,-14.158],[14.403,-14.146],[14.63,-14.049],[14.676,-14.023],[14.889,-13.88],[15.593,-12.753],[14.352,-13.243],[14.171,-13.424],[14.137,-13.465],[14.001,-13.673],[13.983,-13.708],[13.894,-13.921],[13.882,-13.954],[13.83,-14.197],[13.828,-14.219]],"c":true},"ix":2},"nm":"Trazado 2","mn":"ADBE Vector Shape - Group","hd":false},{"ind":2,"ty":"sh","ix":3,"ks":{"a":0,"k":{"i":[[0,0],[0,0],[1.319,2.754],[1.677,1.227],[-0.086,0.101],[-0.136,0.084],[-0.02,-0.07],[-0.006,-0.018],[-0.022,-0.056],[-0.01,-0.022],[-0.034,-0.061],[-0.004,-0.007],[-0.046,-0.065],[-0.013,-0.016],[-0.04,-0.046],[-0.015,-0.016],[-0.062,-0.052],[-0.616,0.292],[-0.087,0.101],[0.57,0.474],[0.067,0.044],[0.02,0.013],[0.052,0.027],[0.019,0.009],[0.074,0.027],[0.011,0.003],[0.066,0.015],[0.023,0.005],[0.061,0.007],[0.018,0.002],[0.074,0],[-0.105,0.125],[-0.64,-0.531],[-0.133,0.156],[0.155,0.128],[0.802,-0.947],[0.072,-0.379],[0.25,-0.298],[0.071,-0.129],[5.743,-2.747],[0.498,-0.298],[0,0],[-0.349,-0.381],[0,0],[0.285,-3.576],[0.012,0],[0,0],[-0.32,-0.438],[0,0],[-0.25,-0.071],[-2.616,0.222],[-2.391,-0.588],[0,0],[-0.389,0.185],[0,0],[0.246,0.517],[0,0],[-1.328,0.635],[-1.374,1.291],[0,0],[-0.51,0.242],[0,0],[0.028,0.419]],"o":[[0,0],[0.727,-2.914],[-0.92,-1.925],[0.055,-0.113],[0.105,-0.125],[0.013,0.073],[0.005,0.018],[0.018,0.059],[0.01,0.021],[0.028,0.063],[0.004,0.008],[0.04,0.069],[0.013,0.016],[0.036,0.049],[0.015,0.016],[0.055,0.058],[0.486,0.403],[0.104,-0.049],[0.584,-0.694],[-0.062,-0.05],[-0.018,-0.011],[-0.051,-0.031],[-0.02,-0.01],[-0.071,-0.033],[-0.01,-0.004],[-0.064,-0.022],[-0.024,-0.005],[-0.06,-0.012],[-0.02,-0.003],[-0.075,-0.007],[0.059,-0.147],[0.541,-0.64],[0.154,0.128],[0.131,-0.155],[-0.95,-0.787],[-0.252,0.3],[-0.364,0.136],[-0.1,0.117],[-4.466,-2.907],[-0.535,0.256],[0,0],[-0.517,0.013],[0,0],[-2.812,2.807],[-0.011,0],[-0.398,2.446],[-0.359,0.41],[0,0],[0.152,0.21],[0,0],[1.724,1.6],[0,0],[0.311,0.29],[0,0],[0.522,-0.249],[0,0],[1.36,-0.307],[1.83,-0.875],[0,0],[0.241,0.509],[0,0],[0.378,-0.18],[0,0]],"v":[[17.44,0.012],[17.31,0.092],[16.517,-8.611],[12.546,-13.357],[12.751,-13.682],[13.115,-13.997],[13.166,-13.784],[13.183,-13.73],[13.243,-13.557],[13.27,-13.493],[13.363,-13.305],[13.375,-13.283],[13.504,-13.083],[13.542,-13.036],[13.658,-12.895],[13.704,-12.846],[13.878,-12.682],[15.867,-12.063],[16.156,-12.288],[15.363,-14.441],[15.17,-14.581],[15.111,-14.618],[14.956,-14.706],[14.897,-14.736],[14.679,-14.826],[14.648,-14.835],[14.452,-14.891],[14.382,-14.906],[14.202,-14.936],[14.145,-14.943],[13.924,-14.954],[14.171,-15.365],[16.311,-15.563],[16.829,-15.611],[16.785,-16.124],[13.611,-15.833],[13.126,-14.801],[12.19,-14.148],[11.935,-13.777],[-4.611,-14.383],[-6.162,-13.549],[-10.33,-13.9],[-10.761,-12.893],[-9.755,-10.755],[-14.551,-0.818],[-14.584,-0.819],[-17.705,3.484],[-17.774,4.932],[-14.695,9.158],[-14.074,9.59],[-10.623,9.419],[-4.344,12.729],[-0.06,16.77],[1.1,16.945],[3.859,15.635],[4.36,14.251],[3.65,12.755],[7.696,11.346],[12.518,8.059],[13.432,9.986],[14.793,10.469],[17.486,9.191],[18.066,8.199]],"c":true},"ix":2},"nm":"Trazado 3","mn":"ADBE Vector Shape - Group","hd":false},{"ty":"mm","mm":1,"nm":"Combinar trazados 1","mn":"ADBE Vector Filter - Merge","hd":false},{"ty":"fl","c":{"a":0,"k":[0.019999999626,0.745000023935,0.313999998803,1],"ix":4},"o":{"a":0,"k":100,"ix":5},"r":1,"bm":0,"nm":"Relleno 1","mn":"ADBE Vector Graphic - Fill","hd":false},{"ty":"tr","p":{"a":0,"k":[73.051,72.767],"ix":2},"a":{"a":0,"k":[0,0],"ix":1},"s":{"a":0,"k":[100,100],"ix":3},"r":{"a":0,"k":0,"ix":6},"o":{"a":0,"k":100,"ix":7},"sk":{"a":0,"k":0,"ix":4},"sa":{"a":0,"k":0,"ix":5},"nm":"Transformar"}],"nm":"Grupo 1","np":7,"cix":2,"bm":0,"ix":1,"mn":"ADBE Vector Group","hd":false}],"ip":0,"op":120,"st":0,"bm":0},{"ddd":0,"ind":8,"ty":4,"nm":"screen contornos","sr":1,"ks":{"o":{"a":1,"k":[{"i":{"x":[0.833],"y":[0.833]},"o":{"x":[0.167],"y":[0.167]},"t":0,"s":[0]},{"t":10,"s":[100]}],"ix":11},"r":{"a":0,"k":0,"ix":10},"p":{"a":0,"k":[86,97.592,0],"ix":2,"l":2},"a":{"a":0,"k":[86,97.592,0],"ix":1,"l":2},"s":{"a":0,"k":[100,100,100],"ix":6,"l":2}},"ao":0,"shapes":[{"ty":"gr","it":[{"ind":0,"ty":"sh","ix":1,"ks":{"a":0,"k":{"i":[[0,0],[0,0],[0,0],[0,0]],"o":[[0,0],[0,0],[0,0],[0,0]],"v":[[50.799,31.736],[-6.267,59.569],[-50.799,-31.735],[6.268,-59.568]],"c":true},"ix":2},"nm":"Trazado 1","mn":"ADBE Vector Shape - Group","hd":false},{"ty":"fl","c":{"a":0,"k":[1,1,1,1],"ix":4},"o":{"a":0,"k":100,"ix":5},"r":1,"bm":0,"nm":"Relleno 1","mn":"ADBE Vector Graphic - Fill","hd":false},{"ty":"tr","p":{"a":0,"k":[82.353,85.292],"ix":2},"a":{"a":0,"k":[0,0],"ix":1},"s":{"a":0,"k":[100,100],"ix":3},"r":{"a":0,"k":0,"ix":6},"o":{"a":0,"k":100,"ix":7},"sk":{"a":0,"k":0,"ix":4},"sa":{"a":0,"k":0,"ix":5},"nm":"Transformar"}],"nm":"Grupo 1","np":4,"cix":2,"bm":0,"ix":1,"mn":"ADBE Vector Group","hd":false}],"ip":0,"op":120,"st":0,"bm":0},{"ddd":0,"ind":9,"ty":4,"nm":"dot contornos","sr":1,"ks":{"o":{"a":1,"k":[{"i":{"x":[0.833],"y":[0.833]},"o":{"x":[0.167],"y":[0.167]},"t":0,"s":[0]},{"t":10,"s":[100]}],"ix":11},"r":{"a":0,"k":0,"ix":10},"p":{"a":0,"k":[86,97.592,0],"ix":2,"l":2},"a":{"a":0,"k":[86,97.592,0],"ix":1,"l":2},"s":{"a":0,"k":[100,100,100],"ix":6,"l":2}},"ao":0,"shapes":[{"ty":"gr","it":[{"ind":0,"ty":"sh","ix":1,"ks":{"a":0,"k":{"i":[[1.281,2.625],[-2.626,1.281],[-1.281,-2.626],[2.625,-1.282]],"o":[[-1.28,-2.626],[2.625,-1.28],[1.28,2.625],[-2.626,1.28]],"v":[[-4.755,2.319],[-2.318,-4.755],[4.755,-2.319],[2.319,4.755]],"c":true},"ix":2},"nm":"Trazado 1","mn":"ADBE Vector Shape - Group","hd":false},{"ty":"fl","c":{"a":0,"k":[0,0.118000000598,0.372999991623,1],"ix":4},"o":{"a":0,"k":100,"ix":5},"r":1,"bm":0,"nm":"Relleno 1","mn":"ADBE Vector Graphic - Fill","hd":false},{"ty":"tr","p":{"a":0,"k":[108.33,138.552],"ix":2},"a":{"a":0,"k":[0,0],"ix":1},"s":{"a":0,"k":[100,100],"ix":3},"r":{"a":0,"k":0,"ix":6},"o":{"a":0,"k":100,"ix":7},"sk":{"a":0,"k":0,"ix":4},"sa":{"a":0,"k":0,"ix":5},"nm":"Transformar"}],"nm":"Grupo 1","np":4,"cix":2,"bm":0,"ix":1,"mn":"ADBE Vector Group","hd":false}],"ip":0,"op":120,"st":0,"bm":0},{"ddd":0,"ind":10,"ty":4,"nm":"phone contornos","sr":1,"ks":{"o":{"a":1,"k":[{"i":{"x":[0.833],"y":[0.833]},"o":{"x":[0.167],"y":[0.167]},"t":0,"s":[0]},{"t":10,"s":[100]}],"ix":11},"r":{"a":0,"k":0,"ix":10},"p":{"a":0,"k":[86,97.592,0],"ix":2,"l":2},"a":{"a":0,"k":[86,97.592,0],"ix":1,"l":2},"s":{"a":0,"k":[100,100,100],"ix":6,"l":2}},"ao":0,"shapes":[{"ty":"gr","it":[{"ind":0,"ty":"sh","ix":1,"ks":{"a":0,"k":{"i":[[4.202,-2.05],[0,0],[2.049,4.203],[0,0],[-4.202,2.05],[0,0],[-2.049,-4.203],[0,0]],"o":[[0,0],[-4.202,2.049],[0,0],[-2.05,-4.203],[0,0],[4.203,-2.049],[0,0],[2.05,4.202]],"v":[[53.025,45.956],[3.568,70.078],[-7.751,66.18],[-56.923,-34.635],[-53.025,-45.955],[-3.569,-70.077],[7.751,-66.179],[56.922,34.636]],"c":true},"ix":2},"nm":"Trazado 1","mn":"ADBE Vector Shape - Group","hd":false},{"ty":"fl","c":{"a":0,"k":[0,0.224000010771,0.651000019148,1],"ix":4},"o":{"a":0,"k":100,"ix":5},"r":1,"bm":0,"nm":"Relleno 1","mn":"ADBE Vector Graphic - Fill","hd":false},{"ty":"tr","p":{"a":0,"k":[84.208,89.096],"ix":2},"a":{"a":0,"k":[0,0],"ix":1},"s":{"a":0,"k":[100,100],"ix":3},"r":{"a":0,"k":0,"ix":6},"o":{"a":0,"k":100,"ix":7},"sk":{"a":0,"k":0,"ix":4},"sa":{"a":0,"k":0,"ix":5},"nm":"Transformar"}],"nm":"Grupo 1","np":4,"cix":2,"bm":0,"ix":1,"mn":"ADBE Vector Group","hd":false}],"ip":0,"op":120,"st":0,"bm":0},{"ddd":0,"ind":11,"ty":4,"nm":"base contornos","sr":1,"ks":{"o":{"a":1,"k":[{"i":{"x":[0.833],"y":[0.833]},"o":{"x":[0.167],"y":[0.167]},"t":0,"s":[0]},{"t":10,"s":[100]}],"ix":11},"r":{"a":0,"k":0,"ix":10},"p":{"a":0,"k":[86,97.592,0],"ix":2,"l":2},"a":{"a":0,"k":[86,97.592,0],"ix":1,"l":2},"s":{"a":0,"k":[100,100,100],"ix":6,"l":2}},"ao":0,"shapes":[{"ty":"gr","it":[{"ind":0,"ty":"sh","ix":1,"ks":{"a":0,"k":{"i":[[0,-47.497],[47.497,0],[0,47.497],[-47.497,0]],"o":[[0,47.497],[-47.497,0],[0,-47.497],[47.497,0]],"v":[[86,0],[0,86],[-86,0],[0,-86]],"c":true},"ix":2},"nm":"Trazado 1","mn":"ADBE Vector Shape - Group","hd":false},{"ty":"fl","c":{"a":0,"k":[0.513999968884,0.764999988032,0.922000002394,1],"ix":4},"o":{"a":0,"k":100,"ix":5},"r":1,"bm":0,"nm":"Relleno 1","mn":"ADBE Vector Graphic - Fill","hd":false},{"ty":"tr","p":{"a":0,"k":[86,86.408],"ix":2},"a":{"a":0,"k":[0,0],"ix":1},"s":{"a":0,"k":[100,100],"ix":3},"r":{"a":0,"k":0,"ix":6},"o":{"a":0,"k":100,"ix":7},"sk":{"a":0,"k":0,"ix":4},"sa":{"a":0,"k":0,"ix":5},"nm":"Transformar"}],"nm":"Grupo 1","np":4,"cix":2,"bm":0,"ix":1,"mn":"ADBE Vector Group","hd":false}],"ip":0,"op":120,"st":0,"bm":0}],"markers":[]}